{
	"src":"maptiles/Walls.png",
	"walls":[
		{
			"name":"Bricks",
			"f_close":[0,0,48,48],
			"f_mid":[48,0,32,32],
			"f_far":[48,32,16,16],
			"s_close":[0,48,8,64],
			"s_mid":[8,48,8,64],
			"s_far":[16,48,9,64]
		},
		{
			"name":"Wood",
			"f_close":[80,0,48,48],
			"f_mid":[128,0,32,32],
			"f_far":[128,32,16,16],
			"s_close":[80,48,8,64],
			"s_mid":[88,48,8,64],
			"s_far":[96,48,9,64]
		},
		{
			"name":"Daub",
			"f_close":[160,0,48,48],
			"f_mid":[208,0,32,32],
			"f_far":[208,32,16,16],
			"s_close":[160,48,8,64],
			"s_mid":[168,48,8,64],
			"s_far":[176,48,9,64]
		}
	],
	"doors":[
		{
			"name":"Wood Framed",
			"open":{
				"f_close":[0,112,48,48],
				"f_mid":[48,112,32,32],
				"f_far":[48,144,16,16],
				"s_close":[0,48,8,64],
				"s_mid":[8,48,8,64],
				"s_far":[16,48,9,64]
			},
			"closed":{
				"f_close":[80,112,48,48],
				"f_mid":[128,112,32,32],
				"f_far":[128,144,16,16],
				"s_close":[80,160,8,64],
				"s_mid":[88,160,8,64],
				"s_far":[96,160,9,64]
			}
		}
	]
}
